neon_synth/__init__.py
neon_synth/effects-toggle.html
neon_synth/layout.html
neon_synth/sidebar.html
neon_synth/theme-toggle.html
neon_synth/theme.conf
neon_synth/static/css/code-blocks.css
neon_synth/static/css/components.css
neon_synth/static/css/neon-synth.css
neon_synth/static/css/responsive.css
neon_synth/static/fonts/.gitkeep
neon_synth/static/js/neon-synth.js
neon_synth/static/js/theme-toggle.js
neon_synth-1.0.1.dist-info/METADATA
neon_synth-1.0.1.dist-info/WHEEL
neon_synth-1.0.1.dist-info/entry_points.txt
neon_synth-1.0.1.dist-info/licenses/LICENSE
neon_synth-1.0.1.dist-info/RECORD
