Metadata-Version: 2.4
Name: neon-synth
Version: 1.0.1
Summary: Neon Synth Sphinx theme with dark/light/system modes
Project-URL: Homepage, https://github.com/nutsloop/neon-synth
Project-URL: Documentation, https://github.com/nutsloop/neon-synth/#readme
Author-email: Simone Del Popolo <inbox@simonedelpopolo.com>
License-Expression: Apache-2.0
License-File: LICENSE
Keywords: documentation,neon,neon-synth,sphinx,theme
Classifier: Development Status :: 4 - Beta
Classifier: Framework :: Sphinx
Classifier: Framework :: Sphinx :: Theme
Classifier: License :: OSI Approved :: Apache Software License
Classifier: Programming Language :: Python :: 3
Classifier: Programming Language :: Python :: 3.10
Classifier: Programming Language :: Python :: 3.11
Classifier: Programming Language :: Python :: 3.12
Classifier: Topic :: Documentation :: Sphinx
Requires-Python: >=3.10
Requires-Dist: sphinx>=7.0
